ipcompacter/__init__.py
ipcompacter/ipcompacter.py
ipcompacter-0.5.dist-info/LICENSE
ipcompacter-0.5.dist-info/METADATA
ipcompacter-0.5.dist-info/WHEEL
ipcompacter-0.5.dist-info/top_level.txt
ipcompacter-0.5.dist-info/RECORD
