Metadata-Version: 2.1
Name: ipcompacter
Version: 0.5
Summary: pacote para monitorar ip e URL
Author: Bryan Victor
Author-email: bryanvictor@ufpi.edu.br
Classifier: Programming Language :: Python :: 3
Classifier: License :: OSI Approved :: MIT License
Classifier: Operating System :: OS Independent
Requires-Python: >=3.8
License-File: LICENSE
